LICENSE
expiring_lru_cache/__init__.py
expiring_lru_cache/version.py
expiring_lru_cache-0.1.1.dist-info/LICENSE
expiring_lru_cache-0.1.1.dist-info/METADATA
expiring_lru_cache-0.1.1.dist-info/WHEEL
expiring_lru_cache-0.1.1.dist-info/RECORD
