Metadata-Version: 2.1
Name: expiring-lru-cache
Version: 0.1.1
Summary: LRU caching with expiration period.
Home-page: https://datarootsio.github.io/expiring-lru-cache/
License: MIT
Keywords: caching,expiration,drop-in,replacement
Author: Murilo Kuniyoshi Suzart Cunha
Author-email: murilo@dataroots.io
Requires-Python: >=3.7,<4.0
Classifier: License :: OSI Approved :: MIT License
Classifier: Programming Language :: Python :: 3
Classifier: Programming Language :: Python :: 3.7
Classifier: Programming Language :: Python :: 3.8
Classifier: Programming Language :: Python :: 3.9
Classifier: Programming Language :: Python :: 3.10
Classifier: Programming Language :: Python :: 3.11
Classifier: Programming Language :: Python :: 3.12
Project-URL: Repository, https://github.com/datarootsio/expiring-lru-cache
